Metadata-Version: 2.1
Name: limedio
Version: 0.0.2
Summary: Limedio Library
Home-page: https://github.com/uec-world-dominators/limedio
Author: shosatojp
Author-email: me@shosato.jp
License: Type license() to see the full license text
Platform: UNKNOWN
Classifier: Programming Language :: Python :: 3
Requires-Python: >=3.6
